<?xml version="1.0"?>
<!--
  ~ Copyright 2004 - 2025 Red Hat, Inc.
  ~
  ~ Licensed under the Apache License, Version 2.0 (the "License");
  ~ you may not use this file except in compliance with the License.
  ~ You may obtain a copy of the License at
  ~
  ~     http://www.apache.org/licenses/LICENSE-2.0
  ~
  ~ Unless required by applicable law or agreed to in writing, software
  ~ distributed under the License is distributed on an "AS IS" basis,
  ~ WITHOUT WARRANTIES OR CONDITIONS OF ANY KIND, either express or implied.
  ~ See the License for the specific language governing permissions and
  ~ limitations under the License.
  -->
<!DOCTYPE hibernate-mapping PUBLIC 
	"-//Hibernate/Hibernate Mapping DTD 3.0//EN"
	"https://www.hibernate.org/dtd/hibernate-mapping-3.0.dtd">

<!-- 

  This mapping demonstrates how to map a collection
  <key> to one of the primary key columns of an
  associated child class with a composite key. This
  is very useful for legacy data!
     
-->

<hibernate-mapping package="org.hibernate.tool.hbm2x.Hbm2HibernateDAOTest">

    <class name="Article">
    
    	<id name="articleId"
    		length="20" type="string">
    		<generator class="assigned"/>
    	</id>
		
		<natural-id>
    		<property name="name" type="string" not-null="true" length="100"/>
    	</natural-id>
    	<property name="content" type="string" not-null="true" length="10000">
    		<meta attribute="default-value">"what can I say"</meta>
    	</property>

		<many-to-one
		    name="author"
            class="org.hibernate.tool.hbm2x.Hbm2HibernateDAOTest.Author"
            cascade="none"
            outer-join="auto"
            update="true"
            insert="true"
            access="property"
            column="authorId" />
		
        <bag name="bagarticles"
    		inverse="true"
    		cascade="save-update">
    		<meta attribute="property-type">java.util.List</meta>
    		<key column="authorId"/>
    		<one-to-many class="Article"/>
    	</bag>
    	
    	 <bag name="bagstrings">
    		
    		<key column="authorId"/>
    		
    		<element type="string"/>
    	</bag>

    	 <map name="AMap">
		  <key column="idx"/>
		  <index type="string"/>
		  <one-to-many class="Article"/>
		</map>
		
		<list name="aList">
		  <key column="idx"/>
		  <list-index/>
		  <one-to-many class="Article"/>		
		</list>

		<set name="sortedArticlesSet" inverse="true"
			sort="comparator.NoopComparator">
			<key column="idx"/>
			<one-to-many class="Article" />
		</set>
		
		<map name="sortedArticlesMap" inverse="true"
			sort="comparator.NoopComparator">
			<key column="idx"/>
			<map-key type="string"/>
			<one-to-many class="Article" />
		</map>
		
		<map name="naturalSortedArticlesMap" inverse="true"
			sort="natural">
			<key column="idx"/>
			<map-key type="string"/>
			<one-to-many class="Article" />
		</map>
		
    </class>

</hibernate-mapping>
